LICENSE
README.rst
setup.cfg
setup.py
cert_expiration/__init__.py
cert_expiration/__main__.py
cert_expiration.egg-info/PKG-INFO
cert_expiration.egg-info/SOURCES.txt
cert_expiration.egg-info/dependency_links.txt
cert_expiration.egg-info/entry_points.txt
cert_expiration.egg-info/top_level.txt