Metadata-Version: 1.1
Name: cert-expiration
Version: 1.0
Summary: Get certificates expiration dates.
Home-page: https://gitlab.com/aristofor/cert-expiration
Author: Aristofor Kolomb
Author-email: aristofor@gmail.com
License: LGPLv3
Platform: UNKNOWN
Classifier: Development Status :: 5 - Production/Stable
Classifier: Programming Language :: Python :: 3
Classifier: Topic :: Internet :: WWW/HTTP
Classifier: License :: OSI Approved :: GNU Lesser General Public License v3 (LGPLv3)
